src/__init__.py
src/brikeda_robot/__init__.py
src/brikeda_robot/robot.py
src/brikeda_robot/test.py
brikeda_robot-0.0.2.dist-info/LICENSE
brikeda_robot-0.0.2.dist-info/METADATA
brikeda_robot-0.0.2.dist-info/WHEEL
brikeda_robot-0.0.2.dist-info/top_level.txt
brikeda_robot-0.0.2.dist-info/RECORD
