Metadata-Version: 2.1
Name: brikeda-robot
Version: 0.0.2
Summary: Types to control hardware on a Raspberry Pi for robot. Motor Controller,Camera, Range Detector
Home-page: https://github.com/markBosley/brikeda_robot
Author: Mark Bosley
Author-email: mark.bosley@brikeda.com
Classifier: Programming Language :: Python :: 3
Classifier: License :: OSI Approved :: MIT License
Classifier: Operating System :: OS Independent
Requires-Python: >=3.7
License-File: LICENSE
